fakerpy/__init__.py
fakerpy/enums.py
fakerpy/person.py
fakerpy/data/__init__.py
fakerpy/data/city_names_de.json
fakerpy/data/city_names_us.json
fakerpy/data/first_names_de_f.json
fakerpy/data/first_names_de_m.json
fakerpy/data/first_names_us_f.json
fakerpy/data/first_names_us_m.json
fakerpy/data/last_names_de.json
fakerpy/data/last_names_us.json
fakerpy/data/mail_domains.json
fakerpy/data/street_names_de.json
fakerpy/data/street_names_us.json
FakerPy_CediGaming-0.1.1.dist-info/LICENSE
FakerPy_CediGaming-0.1.1.dist-info/METADATA
FakerPy_CediGaming-0.1.1.dist-info/WHEEL
FakerPy_CediGaming-0.1.1.dist-info/top_level.txt
FakerPy_CediGaming-0.1.1.dist-info/RECORD
