Metadata-Version: 2.1
Name: FakerPy-CediGaming
Version: 0.1.1
Summary: Open-source Fake-Data-Generator for Python.
Home-page: https://github.com/CediGaming/FakerPy-CediGaming
Author: CediGaming
Author-email: 
License: UNKNOWN
Project-URL: Bug Tracker, https://github.com/CediGaming/FakerPy-CediGaming/issues
Platform: UNKNOWN
Classifier: Programming Language :: Python :: 3
Classifier: Operating System :: OS Independent
Requires-Python: >=3.8
License-File: LICENSE
